hydrafs/__init__.py
hydrafs-0.1.0.dist-info/METADATA
hydrafs-0.1.0.dist-info/WHEEL
hydrafs-0.1.0.dist-info/RECORD
